{"media_url": "https://raw.githubusercontent.com/rneiss/PocketTorah/master/data/audio/Devarim-3.mp3", "source": "Pocket Torah", "media_type": "Torah Reading", "license": "CC-BY-SA", "source_site": "http://www.pockettorah.com", "description": "Audio recordings of the weekly Torah portions used in PocketTorah. Avery-Binder style.", "ref": [{"sefaria_ref": "Deuteronomy 1:22", "start_time": "2.769909", "end_time": "40.075756"}, {"sefaria_ref": "Deuteronomy 1:23", "start_time": "40.075756", "end_time": "57.722921"}, {"sefaria_ref": "Deuteronomy 1:24", "start_time": "57.722921", "end_time": "73.020820"}, {"sefaria_ref": "Deuteronomy 1:25", "start_time": "73.020820", "end_time": "100.733663"}, {"sefaria_ref": "Deuteronomy 1:26", "start_time": "100.733663", "end_time": "115.885621"}, {"sefaria_ref": "Deuteronomy 1:27", "start_time": "115.885621", "end_time": "142.704838"}, {"sefaria_ref": "Deuteronomy 1:28", "start_time": "142.704838", "end_time": "179.267440"}, {"sefaria_ref": "Deuteronomy 1:29", "start_time": "179.267440", "end_time": "191.739860"}, {"sefaria_ref": "Deuteronomy 1:30", "start_time": "191.739860", "end_time": "217.668885"}, {"sefaria_ref": "Deuteronomy 1:31", "start_time": "217.668885", "end_time": "247.070211"}, {"sefaria_ref": "Deuteronomy 1:32", "start_time": "247.070211", "end_time": "259.910846"}, {"sefaria_ref": "Deuteronomy 1:33", "start_time": "259.910846", "end_time": "291.387394"}, {"sefaria_ref": "Deuteronomy 1:34", "start_time": "291.387394", "end_time": "303.113471"}, {"sefaria_ref": "Deuteronomy 1:35", "start_time": "303.113471", "end_time": "326.160995"}, {"sefaria_ref": "Deuteronomy 1:36", "start_time": "326.160995", "end_time": "354.193335"}, {"sefaria_ref": "Deuteronomy 1:37", "start_time": "354.193335", "end_time": "368.894078"}, {"sefaria_ref": "Deuteronomy 1:38", "start_time": "368.894078", "end_time": "388.12725"}]}