{"media_url": "https://raw.githubusercontent.com/rneiss/PocketTorah/master/data/audio/KiTavo-7.mp3", "source": "Pocket Torah", "media_type": "Torah Reading", "license": "CC-BY-SA", "source_site": "http://www.pockettorah.com", "description": "Audio recordings of the weekly Torah portions used in PocketTorah. Avery-Binder style.", "ref": [{"sefaria_ref": "Deuteronomy 29:1", "start_time": "0", "end_time": "29.924354"}, {"sefaria_ref": "Deuteronomy 29:2", "start_time": "29.924354", "end_time": "45.504943"}, {"sefaria_ref": "Deuteronomy 29:3", "start_time": "45.504943", "end_time": "62.966349"}, {"sefaria_ref": "Deuteronomy 29:4", "start_time": "62.966349", "end_time": "80.822494"}, {"sefaria_ref": "Deuteronomy 29:5", "start_time": "80.822494", "end_time": "98.390748"}, {"sefaria_ref": "Deuteronomy 29:6", "start_time": "98.390748", "end_time": "122.331644"}, {"sefaria_ref": "Deuteronomy 29:7", "start_time": "122.331644", "end_time": "137.749694"}, {"sefaria_ref": "Deuteronomy 29:8", "start_time": "137.749694", "end_time": "156.10775"}]}