{"media_url": "https://raw.githubusercontent.com/rneiss/PocketTorah/master/data/audio/Nasso-6.mp3", "source": "Pocket Torah", "media_type": "Torah Reading", "license": "CC-BY-SA", "source_site": "http://www.pockettorah.com", "description": "Audio recordings of the weekly Torah portions used in PocketTorah. Avery-Binder style.", "ref": [{"sefaria_ref": "Numbers 7:42", "start_time": "0", "end_time": "8.874455"}, {"sefaria_ref": "Numbers 7:43", "start_time": "8.874455", "end_time": "32.393186"}, {"sefaria_ref": "Numbers 7:44", "start_time": "32.393186", "end_time": "38.540306"}, {"sefaria_ref": "Numbers 7:45", "start_time": "38.540306", "end_time": "49.756710"}, {"sefaria_ref": "Numbers 7:46", "start_time": "49.756710", "end_time": "52.911540"}, {"sefaria_ref": "Numbers 7:47", "start_time": "52.911540", "end_time": "74.826552"}, {"sefaria_ref": "Numbers 7:48", "start_time": "74.826552", "end_time": "84.286801"}, {"sefaria_ref": "Numbers 7:49", "start_time": "84.286801", "end_time": "106.807073"}, {"sefaria_ref": "Numbers 7:50", "start_time": "106.807073", "end_time": "112.420134"}, {"sefaria_ref": "Numbers 7:51", "start_time": "112.420134", "end_time": "123.597509"}, {"sefaria_ref": "Numbers 7:52", "start_time": "123.597509", "end_time": "126.492293"}, {"sefaria_ref": "Numbers 7:53", "start_time": "126.492293", "end_time": "142.944447"}, {"sefaria_ref": "Numbers 7:54", "start_time": "142.944447", "end_time": "150.905808"}, {"sefaria_ref": "Numbers 7:55", "start_time": "150.905808", "end_time": "171.586871"}, {"sefaria_ref": "Numbers 7:56", "start_time": "171.586871", "end_time": "176.927460"}, {"sefaria_ref": "Numbers 7:57", "start_time": "176.927460", "end_time": "186.698435"}, {"sefaria_ref": "Numbers 7:58", "start_time": "186.698435", "end_time": "189.669228"}, {"sefaria_ref": "Numbers 7:59", "start_time": "189.669228", "end_time": "207.324194"}, {"sefaria_ref": "Numbers 7:60", "start_time": "207.324194", "end_time": "217.430223"}, {"sefaria_ref": "Numbers 7:61", "start_time": "217.430223", "end_time": "237.645053"}, {"sefaria_ref": "Numbers 7:62", "start_time": "237.645053", "end_time": "242.496482"}, {"sefaria_ref": "Numbers 7:63", "start_time": "242.496482", "end_time": "254.044772"}, {"sefaria_ref": "Numbers 7:64", "start_time": "254.044772", "end_time": "256.736745"}, {"sefaria_ref": "Numbers 7:65", "start_time": "256.736745", "end_time": "273.496926"}, {"sefaria_ref": "Numbers 7:66", "start_time": "273.496926", "end_time": "282.039631"}, {"sefaria_ref": "Numbers 7:67", "start_time": "282.039631", "end_time": "302.542851"}, {"sefaria_ref": "Numbers 7:68", "start_time": "302.542851", "end_time": "307.465482"}, {"sefaria_ref": "Numbers 7:69", "start_time": "307.465482", "end_time": "316.670365"}, {"sefaria_ref": "Numbers 7:70", "start_time": "316.670365", "end_time": "319.592995"}, {"sefaria_ref": "Numbers 7:71", "start_time": "319.592995", "end_time": "339.46125"}]}