{"media_url": "https://raw.githubusercontent.com/rneiss/PocketTorah/master/data/audio/Tetzaveh-7.mp3", "source": "Pocket Torah", "media_type": "Torah Reading", "license": "CC-BY-SA", "source_site": "http://www.pockettorah.com", "description": "Audio recordings of the weekly Torah portions used in PocketTorah. Avery-Binder style.", "ref": [{"sefaria_ref": "Exodus 30:1", "start_time": "0", "end_time": "9.927604"}, {"sefaria_ref": "Exodus 30:2", "start_time": "9.927604", "end_time": "22.103550"}, {"sefaria_ref": "Exodus 30:3", "start_time": "22.103550", "end_time": "40.435292"}, {"sefaria_ref": "Exodus 30:4", "start_time": "40.435292", "end_time": "64.384180"}, {"sefaria_ref": "Exodus 30:5", "start_time": "64.384180", "end_time": "71.926864"}, {"sefaria_ref": "Exodus 30:6", "start_time": "71.926864", "end_time": "90.989323"}, {"sefaria_ref": "Exodus 30:7", "start_time": "90.989323", "end_time": "105.571454"}, {"sefaria_ref": "Exodus 30:8", "start_time": "105.571454", "end_time": "120.517098"}, {"sefaria_ref": "Exodus 30:9", "start_time": "120.517098", "end_time": "133.394509"}, {"sefaria_ref": "Exodus 30:10", "start_time": "133.394509", "end_time": "156.787"}]}