{"media_url": "https://raw.githubusercontent.com/rneiss/PocketTorah/master/data/audio/Vayera-4.mp3", "source": "Pocket Torah", "media_type": "Torah Reading", "license": "CC-BY-SA", "source_site": "http://www.pockettorah.com", "description": "Audio recordings of the weekly Torah portions used in PocketTorah. Avery-Binder style.", "ref": [{"sefaria_ref": "Genesis 19:21", "start_time": "0", "end_time": "12.943298"}, {"sefaria_ref": "Genesis 19:22", "start_time": "12.943298", "end_time": "25.389194"}, {"sefaria_ref": "Genesis 19:23", "start_time": "25.389194", "end_time": "30.311824"}, {"sefaria_ref": "Genesis 19:24", "start_time": "30.311824", "end_time": "41.550283"}, {"sefaria_ref": "Genesis 19:25", "start_time": "41.550283", "end_time": "51.465203"}, {"sefaria_ref": "Genesis 19:26", "start_time": "51.465203", "end_time": "57.014772"}, {"sefaria_ref": "Genesis 19:27", "start_time": "57.014772", "end_time": "65.443616"}, {"sefaria_ref": "Genesis 19:28", "start_time": "65.443616", "end_time": "80.536586"}, {"sefaria_ref": "Genesis 19:29", "start_time": "80.536586", "end_time": "96.465475"}, {"sefaria_ref": "Genesis 19:30", "start_time": "96.465475", "end_time": "113.392822"}, {"sefaria_ref": "Genesis 19:31", "start_time": "113.392822", "end_time": "125.536858"}, {"sefaria_ref": "Genesis 19:32", "start_time": "125.536858", "end_time": "135.451779"}, {"sefaria_ref": "Genesis 19:33", "start_time": "135.451779", "end_time": "151.728967"}, {"sefaria_ref": "Genesis 19:34", "start_time": "151.728967", "end_time": "170.955090"}, {"sefaria_ref": "Genesis 19:35", "start_time": "170.955090", "end_time": "186.117720"}, {"sefaria_ref": "Genesis 19:36", "start_time": "186.117720", "end_time": "191.853049"}, {"sefaria_ref": "Genesis 19:37", "start_time": "191.853049", "end_time": "200.281892"}, {"sefaria_ref": "Genesis 19:38", "start_time": "200.281892", "end_time": "210.359353"}, {"sefaria_ref": "Genesis 20:1", "start_time": "210.359353", "end_time": "222.735589"}, {"sefaria_ref": "Genesis 20:2", "start_time": "222.735589", "end_time": "236.040623"}, {"sefaria_ref": "Genesis 20:3", "start_time": "236.040623", "end_time": "250.019035"}, {"sefaria_ref": "Genesis 20:4", "start_time": "250.019035", "end_time": "260.050056"}, {"sefaria_ref": "Genesis 20:5", "start_time": "260.050056", "end_time": "272.286972"}, {"sefaria_ref": "Genesis 20:6", "start_time": "272.286972", "end_time": "293.626110"}, {"sefaria_ref": "Genesis 20:7", "start_time": "293.626110", "end_time": "309.554999"}, {"sefaria_ref": "Genesis 20:8", "start_time": "309.554999", "end_time": "323.208332"}, {"sefaria_ref": "Genesis 20:9", "start_time": "323.208332", "end_time": "346.312187"}, {"sefaria_ref": "Genesis 20:10", "start_time": "346.312187", "end_time": "353.696133"}, {"sefaria_ref": "Genesis 20:11", "start_time": "353.696133", "end_time": "363.959353"}, {"sefaria_ref": "Genesis 20:12", "start_time": "363.959353", "end_time": "373.781394"}, {"sefaria_ref": "Genesis 20:13", "start_time": "373.781394", "end_time": "397.163888"}, {"sefaria_ref": "Genesis 20:14", "start_time": "397.163888", "end_time": "409.609784"}, {"sefaria_ref": "Genesis 20:15", "start_time": "409.609784", "end_time": "417.318809"}, {"sefaria_ref": "Genesis 20:16", "start_time": "417.318809", "end_time": "433.410237"}, {"sefaria_ref": "Genesis 20:17", "start_time": "433.410237", "end_time": "445.298854"}, {"sefaria_ref": "Genesis 20:18", "start_time": "445.298854", "end_time": "454.238536"}, {"sefaria_ref": "Genesis 21:1", "start_time": "454.238536", "end_time": "465.848514"}, {"sefaria_ref": "Genesis 21:2", "start_time": "465.848514", "end_time": "477.783570"}, {"sefaria_ref": "Genesis 21:3", "start_time": "477.783570", "end_time": "486.421394"}, {"sefaria_ref": "Genesis 21:4", "start_time": "486.421394", "end_time": "497.42375"}]}