{"media_url": "https://raw.githubusercontent.com/rneiss/PocketTorah/master/data/audio/Yitro-1.mp3", "source": "Pocket Torah", "media_type": "Torah Reading", "license": "CC-BY-SA", "source_site": "http://www.pockettorah.com", "description": "Audio recordings of the weekly Torah portions used in PocketTorah. Avery-Binder style.", "ref": [{"sefaria_ref": "Exodus 18:1", "start_time": "2.001285", "end_time": "25.305234"}, {"sefaria_ref": "Exodus 18:2", "start_time": "25.305234", "end_time": "38.070525"}, {"sefaria_ref": "Exodus 18:3", "start_time": "38.070525", "end_time": "52.776496"}, {"sefaria_ref": "Exodus 18:4", "start_time": "52.776496", "end_time": "63.397573"}, {"sefaria_ref": "Exodus 18:5", "start_time": "63.397573", "end_time": "82.583089"}, {"sefaria_ref": "Exodus 18:6", "start_time": "82.583089", "end_time": "96.616804"}, {"sefaria_ref": "Exodus 18:7", "start_time": "96.616804", "end_time": "113.501485"}, {"sefaria_ref": "Exodus 18:8", "start_time": "113.501485", "end_time": "139.036085"}, {"sefaria_ref": "Exodus 18:9", "start_time": "139.036085", "end_time": "153.341505"}, {"sefaria_ref": "Exodus 18:10", "start_time": "153.341505", "end_time": "178.251568"}, {"sefaria_ref": "Exodus 18:11", "start_time": "178.251568", "end_time": "191.376243"}, {"sefaria_ref": "Exodus 18:12", "start_time": "191.376243", "end_time": "218.80175"}]}